levitate/__init__.py
levitate/_indexing.py
levitate/_version.py
levitate/analysis.py
levitate/arrays.py
levitate/materials.py
levitate/optimization.py
levitate/transducers.py
levitate/visualizers.py
levitate/fields/__init__.py
levitate/fields/_implementations.py
levitate/fields/_transformers.py
levitate/fields/_wrappers.py
levitate/hardware/CyclicUltrahapticsArray.cpp
levitate/hardware/CyclicUltrahapticsArray.hpp
levitate/hardware/TCPArray.cpp
levitate/hardware/__init__.py
levitate/hardware/_interactlab.py
levitate/hardware/_ultraleap.py
levitate/hardware/array_control.cpp
levitate/hardware/make.bat
levitate/hardware/makefile
levitate-3.0.0.dist-info/LICENSE.txt
levitate-3.0.0.dist-info/METADATA
levitate-3.0.0.dist-info/WHEEL
levitate-3.0.0.dist-info/top_level.txt
levitate-3.0.0.dist-info/RECORD
