Metadata-Version: 2.1
Name: levitate
Version: 3.0.0
Summary: Python implementations from the Levitate research project
Home-page: https://github.com/AppliedAcousticsChalmers/levitate
Author: Carl Andersson
Author-email: carl.andersson@chalmers.se
License: MIT
Platform: UNKNOWN
Requires-Python: >=3.6
License-File: LICENSE.txt
Requires-Dist: numpy
Requires-Dist: scipy
